cobblestone/Dockerfile
cobblestone/__init__.py
cobblestone/config.py
cobblestone/database_mongo.py
cobblestone/database_neo4j.py
cobblestone/database_sql.py
cobblestone/run.py
cobblestone/security.py
cobblestone/server.py
cobblestone/tokens.py
cobblestone/controllers/__init__.py
cobblestone/controllers/auth_db.py
cobblestone/controllers/auth_keycloak.py
cobblestone/controllers/mongo/__init__.py
cobblestone/controllers/mongo/users.py
cobblestone/controllers/neo4j/__init__.py
cobblestone/controllers/neo4j/users.py
cobblestone/controllers/sql/__init__.py
cobblestone/controllers/sql/users.py
cobblestone/helpers/__init__.py
cobblestone/helpers/types.py
cobblestone/helpers/utils.py
cobblestone/helpers/mongo/__init__.py
cobblestone/helpers/mongo/converters.py
cobblestone/helpers/mongo/tools.py
cobblestone/helpers/mongo/autorouting/__init__.py
cobblestone/helpers/mongo/autorouting/create.py
cobblestone/helpers/mongo/autorouting/delete.py
cobblestone/helpers/mongo/autorouting/read.py
cobblestone/helpers/mongo/autorouting/update.py
cobblestone/helpers/neo4j/__init__.py
cobblestone/helpers/neo4j/converters.py
cobblestone/helpers/neo4j/tools.py
cobblestone/helpers/neo4j/autorouting/__init__.py
cobblestone/helpers/neo4j/autorouting/create.py
cobblestone/helpers/neo4j/autorouting/delete.py
cobblestone/helpers/neo4j/autorouting/read.py
cobblestone/helpers/neo4j/autorouting/update.py
cobblestone/helpers/sql/__init__.py
cobblestone/helpers/sql/converters.py
cobblestone/helpers/sql/tools.py
cobblestone/helpers/sql/autorouting/__init__.py
cobblestone/helpers/sql/autorouting/create.py
cobblestone/helpers/sql/autorouting/delete.py
cobblestone/helpers/sql/autorouting/read.py
cobblestone/helpers/sql/autorouting/update.py
cobblestone/models/__init__.py
cobblestone/models/mongo/__init__.py
cobblestone/models/mongo/user.py
cobblestone/models/neo4j/__init__.py
cobblestone/models/neo4j/user.py
cobblestone/models/sql/__init__.py
cobblestone/models/sql/user.py
cobblestone/routes/__init__.py
mp.cobblestone-1.3.0.dist-info/LICENSE
mp.cobblestone-1.3.0.dist-info/METADATA
mp.cobblestone-1.3.0.dist-info/WHEEL
mp.cobblestone-1.3.0.dist-info/entry_points.txt
mp.cobblestone-1.3.0.dist-info/top_level.txt
mp.cobblestone-1.3.0.dist-info/RECORD
