Metadata-Version: 2.1
Name: mp.cobblestone
Version: 1.3.0
Summary: A user-friendly tool to create a database-abstraction REST API.
Author: Mina Pêcheux
Author-email: mina.pecheux@gmail.com
License: Apache Software License
Platform: UNKNOWN
Classifier: Development Status :: 3 - Alpha
Classifier: License :: OSI Approved :: Apache Software License
Classifier: Intended Audience :: Developers
Classifier: Programming Language :: Python
Classifier: Programming Language :: Python :: 3
Classifier: Topic :: Database
Classifier: Topic :: Internet :: WWW/HTTP :: HTTP Servers
Classifier: Topic :: Software Development
Classifier: Topic :: Software Development :: Code Generators
Classifier: Topic :: Utilities
Requires-Python: >=3.6
License-File: LICENSE
Requires-Dist: click (==7.1.2)
Requires-Dist: docker (==4.3.1)
Requires-Dist: prompt-toolkit (==1.0.14)
Requires-Dist: PyInquirer (==1.0.3)
